Metadata-Version: 2.4
Name: ue4-docker
Version: 0.0.117
Summary: Windows and Linux containers for Unreal Engine
Author-email: Adam Rehn <adam@adamrehn.com>, Marat Radchenko <marat@slonopotamus.org>
License: MIT License
Project-URL: homepage, https://github.com/adamrehn/ue4-docker
Project-URL: documentation, https://adamrehn.github.io/ue4-docker
Project-URL: repository, https://github.com/adamrehn/ue4-docker.git
Keywords: unreal engine,docker
Classifier: Development Status :: 5 - Production/Stable
Classifier: Environment :: Console
Classifier: Intended Audience :: Developers
Classifier: License :: OSI Approved :: MIT License
Classifier: Programming Language :: Python :: 3
Classifier: Topic :: Software Development :: Build Tools
Requires-Python: >=3.8
License-File: LICENSE
Requires-Dist: colorama
Requires-Dist: docker>=6.1.0
Requires-Dist: humanfriendly
Requires-Dist: Jinja2>=2.11.3
Requires-Dist: packaging>=19.1
Requires-Dist: psutil
Requires-Dist: termcolor
Dynamic: license-file
